Metadata-Version: 2.1
Name: pycosnippets
Version: 0.1.0
Summary: Python Code Snippets
Home-page: https://github.com/rhdzmota/pycosnippets
Author: rhdzmota
Author-email: contact@rhdzmota.com
License: MIT
Platform: UNKNOWN
Classifier: Programming Language :: Python :: 3.7
Requires-Python: >=3.7, <3.8
